magicbell/__init__.py
magicbell/_version.py
magicbell/api/__init__.py
magicbell/api/_base.py
magicbell/api/_parsing.py
magicbell/api/channels.py
magicbell/api/graphql.py
magicbell/api/project.py
magicbell/api/realtime.py
magicbell/api/user.py
magicbell/client.py
magicbell/configuration.py
magicbell/errors.py
magicbell/model/__init__.py
magicbell/model/_base.py
magicbell/model/channels.py
magicbell/model/notification.py
magicbell/model/project.py
magicbell/model/response.py
magicbell/model/user.py
magicbell/model/workspace.py
magicbell-1.1.1.dist-info/LICENSE
magicbell-1.1.1.dist-info/WHEEL
magicbell-1.1.1.dist-info/METADATA
magicbell-1.1.1.dist-info/RECORD
