Metadata-Version: 2.1
Name: magicbell
Version: 1.1.1
Summary: Unofficial Python SDK for MagicBell
Home-page: https://github.com/noteable-io/magicbell-python-sdk
License: MIT
Keywords: magicbell,sdk
Author: Elijah Wilson
Author-email: eli@noteable.io
Requires-Python: >=3.8,<4.0
Classifier: License :: OSI Approved :: MIT License
Classifier: Programming Language :: Python :: 3
Classifier: Programming Language :: Python :: 3.10
Classifier: Programming Language :: Python :: 3.8
Classifier: Programming Language :: Python :: 3.9
Requires-Dist: httpx (>=0.23.0,<0.24.0)
Requires-Dist: orjson (>=3.7.6,<4.0.0)
Requires-Dist: pydantic (>=1.9.0,<2.0.0)
Project-URL: Repository, https://github.com/noteable-io/magicbell-python-sdk
